{
  "related_search_result": [],
  "paging": {
    "is_end": false,
    "next": "http://www.zhihu.com/search_v3?content_length=150&correction=1&search_hash_id=392f7cdc8a9b2bc4641542fbdacdfeae&q=%E6%B7%B1%E5%BA%A6%E5%AD%A6%E4%B9%A0&limit=10&t=column&offset=90&topic_filter=0",
    "previous": "http://www.zhihu.com/search_v3?content_length=150&correction=1&search_hash_id=392f7cdc8a9b2bc4641542fbdacdfeae&q=%E6%B7%B1%E5%BA%A6%E5%AD%A6%E4%B9%A0&limit=10&t=column&offset=70&topic_filter=0"
  },
  "data": [
    {
      "highlight": {
        "content": "",
        "description": "",
        "title": "freestyle之<em>深度学习</em>"
      },
      "object": {
        "description": "",
        "is_following": false,
        "id": "c_113274417",
        "articles_count": 0,
        "attached_info_bytes": "OlkKC3BsYWNlaG9sZGVyEiAzOTJmN2NkYzhhOWIyYmM0NjQxNTQyZmJkYWNkZmVhZRgFIgU0NzE1OCoLY18xMTMyNzQ0MTdKDOa3seW6puWtpuS5oFAAWARgAQ==",
        "score": 1.6636359692,
        "title": "freestyle之<em>深度学习</em>",
        "url": "https://api.zhihu.com/columns/c_113274417",
        "author": {
          "badge": [],
          "name": "cskenken",
          "url": "https://api.zhihu.com/people/ab58b85c395f3b78d746c8ac4a3dd8b6",
          "type": "people",
          "avatar_url": "https://pic3.zhimg.com/50/ec9a13ea3b27f8777dd072a730af1d7f_s.jpg",
          "url_token": "yao-jun-feng-57",
          "id": "ab58b85c395f3b78d746c8ac4a3dd8b6"
        },
        "avatar_url": "https://pic3.zhimg.com/4b70deef7_r.jpg",
        "image_url": "https://pic3.zhimg.com/4b70deef7_r.jpg",
        "followers": 9,
        "type": "column"
      },
      "type": "search_result",
      "id": 81
    },
    {
      "highlight": {
        "content": "",
        "description": "",
        "title": "<em>深度学习</em>与我的那些事"
      },
      "object": {
        "description": "",
        "is_following": false,
        "id": "c_115985719",
        "articles_count": 21,
        "attached_info_bytes": "OlkKC3BsYWNlaG9sZGVyEiAzOTJmN2NkYzhhOWIyYmM0NjQxNTQyZmJkYWNkZmVhZRgFIgU1MTAwNSoLY18xMTU5ODU3MTlKDOa3seW6puWtpuS5oFAAWARgAQ==",
        "score": 1.6571907997,
        "title": "<em>深度学习</em>与我的那些事",
        "url": "https://api.zhihu.com/columns/c_115985719",
        "author": {
          "badge": [],
          "name": "WILL",
          "url": "https://api.zhihu.com/people/55e4f49cb536f5cc25310359c04491b6",
          "type": "people",
          "avatar_url": "https://pic1.zhimg.com/50/28eb2ce5af074c03e811a63b5e89cff6_s.jpg",
          "url_token": "will-55-30",
          "id": "55e4f49cb536f5cc25310359c04491b6"
        },
        "avatar_url": "https://pic4.zhimg.com/v2-fc1bc74393fbbacf24f1e71a15d37b4a_r.jpg",
        "image_url": "https://pic4.zhimg.com/v2-fc1bc74393fbbacf24f1e71a15d37b4a_r.jpg",
        "followers": 211,
        "type": "column"
      },
      "type": "search_result",
      "id": 82
    },
    {
      "highlight": {
        "content": "",
        "description": "",
        "title": "<em>深度学习</em>算法研发之路"
      },
      "object": {
        "description": "",
        "is_following": false,
        "id": "c_127157667",
        "articles_count": 2,
        "attached_info_bytes": "OlkKC3BsYWNlaG9sZGVyEiAzOTJmN2NkYzhhOWIyYmM0NjQxNTQyZmJkYWNkZmVhZRgFIgU2MTcxOCoLY18xMjcxNTc2NjdKDOa3seW6puWtpuS5oFAAWARgAQ==",
        "score": 1.6509708166,
        "title": "<em>深度学习</em>算法研发之路",
        "url": "https://api.zhihu.com/columns/c_127157667",
        "author": {
          "badge": [],
          "name": "magic",
          "url": "https://api.zhihu.com/people/5ff7afc753a610906b75ffaadd0316a3",
          "type": "people",
          "avatar_url": "https://pic3.zhimg.com/50/v2-c60726b722b379f35c63a64ce11605e2_s.jpg",
          "url_token": "wu-zhi-yang-53",
          "id": "5ff7afc753a610906b75ffaadd0316a3"
        },
        "avatar_url": "https://pic3.zhimg.com/4b70deef7_r.jpg",
        "image_url": "https://pic3.zhimg.com/4b70deef7_r.jpg",
        "followers": 53,
        "type": "column"
      },
      "type": "search_result",
      "id": 83
    },
    {
      "highlight": {
        "content": "",
        "description": "",
        "title": "<em>深度学习</em>实践笔记"
      },
      "object": {
        "description": "",
        "is_following": false,
        "id": "c_88204917",
        "articles_count": 3,
        "attached_info_bytes": "OlgKC3BsYWNlaG9sZGVyEiAzOTJmN2NkYzhhOWIyYmM0NjQxNTQyZmJkYWNkZmVhZRgFIgUzMjMyOSoKY184ODIwNDkxN0oM5rex5bqm5a2m5LmgUABYBGAB",
        "score": 1.6449109316,
        "title": "<em>深度学习</em>实践笔记",
        "url": "https://api.zhihu.com/columns/c_88204917",
        "author": {
          "badge": [],
          "name": "郑一轩",
          "url": "https://api.zhihu.com/people/189c506ffbf817be4cf32fc85ef7ea6a",
          "type": "people",
          "avatar_url": "https://pic4.zhimg.com/50/8cd587f52_s.jpg",
          "url_token": "zheng-yixuan",
          "id": "189c506ffbf817be4cf32fc85ef7ea6a"
        },
        "avatar_url": "https://pic3.zhimg.com/4b70deef7_r.jpg",
        "image_url": "https://pic3.zhimg.com/4b70deef7_r.jpg",
        "followers": 36,
        "type": "column"
      },
      "type": "search_result",
      "id": 84
    },
    {
      "highlight": {
        "content": "",
        "description": "",
        "title": "计算机视觉-<em>深度学习</em>研讨专栏"
      },
      "object": {
        "description": "",
        "is_following": false,
        "id": "c_103012648",
        "articles_count": 0,
        "attached_info_bytes": "OlkKC3BsYWNlaG9sZGVyEiAzOTJmN2NkYzhhOWIyYmM0NjQxNTQyZmJkYWNkZmVhZRgFIgUzODMxOCoLY18xMDMwMTI2NDhKDOa3seW6puWtpuS5oFAAWARgAQ==",
        "score": 1.6356756687,
        "title": "计算机视觉-<em>深度学习</em>研讨专栏",
        "url": "https://api.zhihu.com/columns/c_103012648",
        "author": {
          "badge": [],
          "name": "高小斯",
          "url": "https://api.zhihu.com/people/d3c93ca3ec1dae50b33addb520032147",
          "type": "people",
          "avatar_url": "https://pic4.zhimg.com/50/v2-be898662ff59a8cd01e07ca7f4eab8e1_s.jpg",
          "url_token": "gausian",
          "id": "d3c93ca3ec1dae50b33addb520032147"
        },
        "avatar_url": "https://pic3.zhimg.com/4b70deef7_r.jpg",
        "image_url": "https://pic3.zhimg.com/4b70deef7_r.jpg",
        "followers": 21,
        "type": "column"
      },
      "type": "search_result",
      "id": 85
    },
    {
      "highlight": {
        "content": "",
        "description": "",
        "title": "CS224n: 自然语言处理与<em>深度学习</em>"
      },
      "object": {
        "description": "",
        "is_following": false,
        "id": "c_111841537",
        "articles_count": 0,
        "attached_info_bytes": "OlkKC3BsYWNlaG9sZGVyEiAzOTJmN2NkYzhhOWIyYmM0NjQxNTQyZmJkYWNkZmVhZRgFIgU0NTUwMSoLY18xMTE4NDE1MzdKDOa3seW6puWtpuS5oFAAWARgAQ==",
        "score": 1.6346040964,
        "title": "CS224n: 自然语言处理与<em>深度学习</em>",
        "url": "https://api.zhihu.com/columns/c_111841537",
        "author": {
          "badge": [],
          "name": "致Great",
          "url": "https://api.zhihu.com/people/483684d821a67a8d43ef449ae607ad6b",
          "type": "people",
          "avatar_url": "https://pic3.zhimg.com/50/2d4fb2e3ea4abc09d717d5677e0edb13_s.jpg",
          "url_token": "qiang-yan-48-42",
          "id": "483684d821a67a8d43ef449ae607ad6b"
        },
        "avatar_url": "https://pic3.zhimg.com/4b70deef7_r.jpg",
        "image_url": "https://pic3.zhimg.com/4b70deef7_r.jpg",
        "followers": 17,
        "type": "column"
      },
      "type": "search_result",
      "id": 86
    },
    {
      "highlight": {
        "content": "",
        "description": "",
        "title": "程序员<em>深度学习</em>笔记"
      },
      "object": {
        "description": "",
        "is_following": false,
        "id": "deepLearning-from-programmer-view",
        "articles_count": 7,
        "attached_info_bytes": "Om8KC3BsYWNlaG9sZGVyEiAzOTJmN2NkYzhhOWIyYmM0NjQxNTQyZmJkYWNkZmVhZRgFIgUzNDAxNyohZGVlcExlYXJuaW5nLWZyb20tcHJvZ3JhbW1lci12aWV3Sgzmt7HluqblrabkuaBQAFgEYAE=",
        "score": 1.6325047016,
        "title": "程序员<em>深度学习</em>笔记",
        "url": "https://api.zhihu.com/columns/deepLearning-from-programmer-view",
        "author": {
          "badge": [],
          "name": "王尧",
          "url": "https://api.zhihu.com/people/262d1651f5f8c79b61275a96c35e3d7c",
          "type": "people",
          "avatar_url": "https://pic4.zhimg.com/50/da8e974dc_s.jpg",
          "url_token": "wangyaobupt",
          "id": "262d1651f5f8c79b61275a96c35e3d7c"
        },
        "avatar_url": "https://pic3.zhimg.com/4b70deef7_r.jpg",
        "image_url": "https://pic3.zhimg.com/4b70deef7_r.jpg",
        "followers": 124,
        "type": "column"
      },
      "type": "search_result",
      "id": 87
    },
    {
      "highlight": {
        "content": "",
        "description": "",
        "title": "我的草稿――<em>深度学习</em>与视觉"
      },
      "object": {
        "description": "",
        "is_following": false,
        "id": "c_115254772",
        "articles_count": 1,
        "attached_info_bytes": "OlkKC3BsYWNlaG9sZGVyEiAzOTJmN2NkYzhhOWIyYmM0NjQxNTQyZmJkYWNkZmVhZRgFIgU0OTU1MCoLY18xMTUyNTQ3NzJKDOa3seW6puWtpuS5oFAAWARgAQ==",
        "score": 1.628598094,
        "title": "我的草稿――<em>深度学习</em>与视觉",
        "url": "https://api.zhihu.com/columns/c_115254772",
        "author": {
          "badge": [],
          "name": "刘宇鸣",
          "url": "https://api.zhihu.com/people/f535e3f426d00737ae6ea1c468dd8587",
          "type": "people",
          "avatar_url": "https://pic2.zhimg.com/50/03777937b_s.jpg",
          "url_token": "liu-yu-ming-61",
          "id": "f535e3f426d00737ae6ea1c468dd8587"
        },
        "avatar_url": "https://pic3.zhimg.com/4b70deef7_r.jpg",
        "image_url": "https://pic3.zhimg.com/4b70deef7_r.jpg",
        "followers": 6,
        "type": "column"
      },
      "type": "search_result",
      "id": 88
    },
    {
      "highlight": {
        "content": "",
        "description": "",
        "title": "通俗理解统计<em>学习</em>、<em>深度学习</em>、强化<em>学习</em>"
      },
      "object": {
        "description": "",
        "is_following": false,
        "id": "c_127364494",
        "articles_count": 4,
        "attached_info_bytes": "OlkKC3BsYWNlaG9sZGVyEiAzOTJmN2NkYzhhOWIyYmM0NjQxNTQyZmJkYWNkZmVhZRgFIgU2MTc5MSoLY18xMjczNjQ0OTRKDOa3seW6puWtpuS5oFAAWARgAQ==",
        "score": 1.6217216253,
        "title": "通俗理解统计<em>学习</em>、<em>深度学习</em>、强化<em>学习</em>",
        "url": "https://api.zhihu.com/columns/c_127364494",
        "author": {
          "badge": [],
          "name": "James Zhang",
          "url": "https://api.zhihu.com/people/41ef3139a0d756cb807de72b8b8afeb3",
          "type": "people",
          "avatar_url": "https://pic2.zhimg.com/50/v2-03394b15408031b771325e8338fc5976_s.jpg",
          "url_token": "zhang-lei-99-55",
          "id": "41ef3139a0d756cb807de72b8b8afeb3"
        },
        "avatar_url": "https://pic3.zhimg.com/v2-b9e813b2c7cd3f01febc0affb65c6beb_r.jpg",
        "image_url": "https://pic3.zhimg.com/v2-b9e813b2c7cd3f01febc0affb65c6beb_r.jpg",
        "followers": 17,
        "type": "column"
      },
      "type": "search_result",
      "id": 89
    },
    {
      "highlight": {
        "content": "",
        "description": "",
        "title": "<em>深度学习</em>与自然语言处理<em>学习</em>相关"
      },
      "object": {
        "description": "",
        "is_following": false,
        "id": "nlpdl",
        "articles_count": 2,
        "attached_info_bytes": "OlMKC3BsYWNlaG9sZGVyEiAzOTJmN2NkYzhhOWIyYmM0NjQxNTQyZmJkYWNkZmVhZRgFIgUzODcyNyoFbmxwZGxKDOa3seW6puWtpuS5oFAAWARgAQ==",
        "score": 1.6115715504,
        "title": "<em>深度学习</em>与自然语言处理<em>学习</em>相关",
        "url": "https://api.zhihu.com/columns/nlpdl",
        "author": {
          "badge": [],
          "name": "吴洋",
          "url": "https://api.zhihu.com/people/c64ded7a9663711a04ad5ee0aa4f4c33",
          "type": "people",
          "avatar_url": "https://pic2.zhimg.com/50/8b17a4e2c7663898b0a5e8e5879bcb06_s.jpg",
          "url_token": "wu-yang-6-17",
          "id": "c64ded7a9663711a04ad5ee0aa4f4c33"
        },
        "avatar_url": "https://pic2.zhimg.com/v2-77303d496e332744419e0a1c0652fed1_r.jpg",
        "image_url": "https://pic2.zhimg.com/v2-77303d496e332744419e0a1c0652fed1_r.jpg",
        "followers": 38,
        "type": "column"
      },
      "type": "search_result",
      "id": 90
    }
  ],
  "search_action_info": {
    "attached_info_bytes": "OjYSIDM5MmY3Y2RjOGE5YjJiYzQ2NDE1NDJmYmRhY2RmZWFlSgzmt7HluqblrabkuaBQAFgEYAE=",
    "search_hash_id": "392f7cdc8a9b2bc4641542fbdacdfeae"
  }
}