{
  "related_search_result": [],
  "paging": {
    "is_end": false,
    "next": "http://www.zhihu.com/search_v3?content_length=150&correction=1&search_hash_id=392f7cdc8a9b2bc4641542fbdacdfeae&q=%E6%B7%B1%E5%BA%A6%E5%AD%A6%E4%B9%A0&limit=10&t=column&offset=120&topic_filter=0",
    "previous": "http://www.zhihu.com/search_v3?content_length=150&correction=1&search_hash_id=392f7cdc8a9b2bc4641542fbdacdfeae&q=%E6%B7%B1%E5%BA%A6%E5%AD%A6%E4%B9%A0&limit=10&t=column&offset=100&topic_filter=0"
  },
  "data": [
    {
      "highlight": {
        "content": "贝多芬、莫扎特、肖邦，他们从没有死，只是变成了音乐……",
        "description": "贝多芬、莫扎特、肖邦，他们从没有死，只是变成了音乐……",
        "title": "<em>深度</em>疯子"
      },
      "object": {
        "description": "贝多芬、莫扎特、肖邦，他们从没有死，只是变成了音乐……",
        "is_following": false,
        "id": "deeplunatic",
        "articles_count": 1,
        "attached_info_bytes": "OlkKC3BsYWNlaG9sZGVyEiAzOTJmN2NkYzhhOWIyYmM0NjQxNTQyZmJkYWNkZmVhZRgFIgUyNTE4NioLZGVlcGx1bmF0aWNKDOa3seW6puWtpuS5oFAAWARgAQ==",
        "score": 1.0449937582,
        "title": "<em>深度</em>疯子",
        "url": "https://api.zhihu.com/columns/deeplunatic",
        "author": {
          "badge": [],
          "name": "徐潇然",
          "url": "https://api.zhihu.com/people/d6958836970ec2e0f47895f035527eec",
          "type": "people",
          "avatar_url": "https://pic2.zhimg.com/50/v2-ab7268f07d4a095489a413a1ea31311b_s.jpg",
          "url_token": "deepknower",
          "id": "d6958836970ec2e0f47895f035527eec"
        },
        "avatar_url": "https://pic2.zhimg.com/v2-8772617f302f2cf0f058deb9d8e691bd_r.jpg",
        "image_url": "https://pic2.zhimg.com/v2-8772617f302f2cf0f058deb9d8e691bd_r.jpg",
        "followers": 13,
        "type": "column"
      },
      "type": "search_result",
      "id": 111
    },
    {
      "highlight": {
        "content": "本专栏主要分享常见的机器<em>学习</em>&<em>深度学习</em>面试题，当然也会包括一些如推荐系统、NLP其它涉及到机器学习&深度学习领域的面试题等",
        "description": "本专栏主要分享常见的机器<em>学习</em>&<em>深度学习</em>面试题，当然也会包括一些如推荐系统、NLP其它涉及到机器学习&深度学习领域的面试题等",
        "title": "机器<em>学习</em>面试题总结"
      },
      "object": {
        "description": "本专栏主要分享常见的机器<em>学习</em>&<em>深度学习</em>面试题，当然也会包括一些如推荐系统、NLP其它涉及到机器学习&深度学习领域的面试题等",
        "is_following": false,
        "id": "c_129612503",
        "articles_count": 27,
        "attached_info_bytes": "OlkKC3BsYWNlaG9sZGVyEiAzOTJmN2NkYzhhOWIyYmM0NjQxNTQyZmJkYWNkZmVhZRgFIgU2MzgxMyoLY18xMjk2MTI1MDNKDOa3seW6puWtpuS5oFAAWARgAQ==",
        "score": 0.98484689,
        "title": "机器<em>学习</em>面试题总结",
        "url": "https://api.zhihu.com/columns/c_129612503",
        "author": {
          "badge": [],
          "name": "李理",
          "url": "https://api.zhihu.com/people/a25da100f29c8c73e45d88f0483e04d4",
          "type": "people",
          "avatar_url": "https://pic3.zhimg.com/50/v2-daef103369f86aaff48c642dd046c4fc_s.jpg",
          "url_token": "li-li-31-41-67",
          "id": "a25da100f29c8c73e45d88f0483e04d4"
        },
        "avatar_url": "https://pic3.zhimg.com/v2-389972b755ceef4c3b0dd5d0720d4787_r.jpg",
        "image_url": "https://pic3.zhimg.com/v2-389972b755ceef4c3b0dd5d0720d4787_r.jpg",
        "followers": 2823,
        "type": "column"
      },
      "type": "search_result",
      "id": 112
    },
    {
      "highlight": {
        "content": "「明光村职业技术学院」一群努力磕盐小伙伴的日常Paper阅读笔记分享。欢迎关注机器<em>学习</em>、<em>深度学习</em>、自然语言处理等方向的同好们共同探讨",
        "description": "「明光村职业技术学院」一群努力磕盐小伙伴的日常Paper阅读笔记分享。欢迎关注机器<em>学习</em>、<em>深度学习</em>、自然语言处理等方向的同好们共同探讨",
        "title": "<em>学习</em>ML的皮皮虾"
      },
      "object": {
        "description": "「明光村职业技术学院」一群努力磕盐小伙伴的日常Paper阅读笔记分享。欢迎关注机器<em>学习</em>、<em>深度学习</em>、自然语言处理等方向的同好们共同探讨",
        "is_following": false,
        "id": "bupt-pris731",
        "articles_count": 54,
        "attached_info_bytes": "OloKC3BsYWNlaG9sZGVyEiAzOTJmN2NkYzhhOWIyYmM0NjQxNTQyZmJkYWNkZmVhZRgFIgUzNDYzOCoMYnVwdC1wcmlzNzMxSgzmt7HluqblrabkuaBQAFgEYAE=",
        "score": 0.87386024,
        "title": "<em>学习</em>ML的皮皮虾",
        "url": "https://api.zhihu.com/columns/bupt-pris731",
        "author": {
          "badge": [],
          "name": "Shen",
          "url": "https://api.zhihu.com/people/8fc58baa6a375be9c86bc8ae04f22c1c",
          "type": "people",
          "avatar_url": "https://pic4.zhimg.com/50/684fa5613b3c2e82ae4bf30392549abe_s.jpg",
          "url_token": "ivarsen",
          "id": "8fc58baa6a375be9c86bc8ae04f22c1c"
        },
        "avatar_url": "https://pic2.zhimg.com/v2-9c9a56df0912fd5515d6908dd30d8efd_r.jpg",
        "image_url": "https://pic2.zhimg.com/v2-9c9a56df0912fd5515d6908dd30d8efd_r.jpg",
        "followers": 987,
        "type": "column"
      },
      "type": "search_result",
      "id": 113
    },
    {
      "highlight": {
        "content": "主要目的是研究和<em>学习</em>机器<em>学习</em>在认知方面的进展；可能涉及<em>深度学习</em>，强化学习",
        "description": "主要目的是研究和<em>学习</em>机器<em>学习</em>在认知方面的进展；可能涉及<em>深度学习</em>，强化学习",
        "title": "机器<em>学习</em>优秀论文选读"
      },
      "object": {
        "description": "主要目的是研究和<em>学习</em>机器<em>学习</em>在认知方面的进展；可能涉及<em>深度学习</em>，强化学习",
        "is_following": false,
        "id": "ml-papers",
        "articles_count": 0,
        "attached_info_bytes": "OlcKC3BsYWNlaG9sZGVyEiAzOTJmN2NkYzhhOWIyYmM0NjQxNTQyZmJkYWNkZmVhZRgFIgUzNzM5NyoJbWwtcGFwZXJzSgzmt7HluqblrabkuaBQAFgEYAE=",
        "score": 0.8577316999,
        "title": "机器<em>学习</em>优秀论文选读",
        "url": "https://api.zhihu.com/columns/ml-papers",
        "author": {
          "badge": [],
          "name": "崔向阳",
          "url": "https://api.zhihu.com/people/4d499a14b2408b4980049f35435af6b7",
          "type": "people",
          "avatar_url": "https://pic2.zhimg.com/50/9c70c45de_s.jpg",
          "url_token": "cui-xiang-yang",
          "id": "4d499a14b2408b4980049f35435af6b7"
        },
        "avatar_url": "https://pic3.zhimg.com/4b70deef7_r.jpg",
        "image_url": "https://pic3.zhimg.com/4b70deef7_r.jpg",
        "followers": 159,
        "type": "column"
      },
      "type": "search_result",
      "id": 114
    },
    {
      "highlight": {
        "content": "不定期分享机器<em>学习</em>与<em>深度学习</em>实战代码。",
        "description": "不定期分享机器<em>学习</em>与<em>深度学习</em>实战代码。",
        "title": "机器不<em>学习</em>"
      },
      "object": {
        "description": "不定期分享机器<em>学习</em>与<em>深度学习</em>实战代码。",
        "is_following": false,
        "id": "zhaoyeyu",
        "articles_count": 9,
        "attached_info_bytes": "OlYKC3BsYWNlaG9sZGVyEiAzOTJmN2NkYzhhOWIyYmM0NjQxNTQyZmJkYWNkZmVhZRgFIgUzNzQzOSoIemhhb3lleXVKDOa3seW6puWtpuS5oFAAWARgAQ==",
        "score": 0.8556871414,
        "title": "机器不<em>学习</em>",
        "url": "https://api.zhihu.com/columns/zhaoyeyu",
        "author": {
          "badge": [],
          "name": "天雨粟",
          "url": "https://api.zhihu.com/people/97d929615d936543e9a40895b35fb43c",
          "type": "people",
          "avatar_url": "https://pic2.zhimg.com/50/v2-40322100a2a3d553a8e65f58c2f4c289_s.jpg",
          "url_token": "zhao-xie-yu-30",
          "id": "97d929615d936543e9a40895b35fb43c"
        },
        "avatar_url": "https://pic4.zhimg.com/v2-ee7c55e5b838e4d20894921289fb7979_r.jpg",
        "image_url": "https://pic4.zhimg.com/v2-ee7c55e5b838e4d20894921289fb7979_r.jpg",
        "followers": 1906,
        "type": "column"
      },
      "type": "search_result",
      "id": 115
    },
    {
      "highlight": {
        "content": "com/52mlnet 公众号：我爱机器<em>学习</em>",
        "description": "com/52mlnet 公众号：我爱机器<em>学习</em>",
        "title": "我爱机器<em>学习</em>"
      },
      "object": {
        "description": "com/52mlnet 公众号：我爱机器<em>学习</em>",
        "is_following": false,
        "id": "52mlnet",
        "articles_count": 7,
        "attached_info_bytes": "OlUKC3BsYWNlaG9sZGVyEiAzOTJmN2NkYzhhOWIyYmM0NjQxNTQyZmJkYWNkZmVhZRgFIgUxOTAzOSoHNTJtbG5ldEoM5rex5bqm5a2m5LmgUABYBGAB",
        "score": 0.8312779069,
        "title": "我爱机器<em>学习</em>",
        "url": "https://api.zhihu.com/columns/52mlnet",
        "author": {
          "badge": [],
          "name": "我爱机器学习",
          "url": "https://api.zhihu.com/people/03675ab7bf1c28d3d71d2154abb3ddd1",
          "type": "people",
          "avatar_url": "https://pic2.zhimg.com/50/v2-6b806cd538d0aad97084b4cbe40503b3_s.jpg",
          "url_token": "52ml",
          "id": "03675ab7bf1c28d3d71d2154abb3ddd1"
        },
        "avatar_url": "https://pic2.zhimg.com/v2-56311e3f21100a31b9acb84943d6dace_r.jpg",
        "image_url": "https://pic2.zhimg.com/v2-56311e3f21100a31b9acb84943d6dace_r.jpg",
        "followers": 869,
        "type": "column"
      },
      "type": "search_result",
      "id": 116
    },
    {
      "highlight": {
        "content": "从我发布第一篇《 [机器<em>学习</em>入门] 李宏毅机器<em>学习</em>笔记-1 (Learning",
        "description": "从我发布第一篇《 [机器<em>学习</em>入门] 李宏毅机器<em>学习</em>笔记-1 (Learning",
        "title": "机器<em>学习</em>入门（ 台湾大学李宏毅课程笔记 ）"
      },
      "object": {
        "description": "从我发布第一篇《 [机器<em>学习</em>入门] 李宏毅机器<em>学习</em>笔记-1 (Learning",
        "is_following": false,
        "id": "holeung-ml",
        "articles_count": 8,
        "attached_info_bytes": "OlgKC3BsYWNlaG9sZGVyEiAzOTJmN2NkYzhhOWIyYmM0NjQxNTQyZmJkYWNkZmVhZRgFIgU0OTg0OCoKaG9sZXVuZy1tbEoM5rex5bqm5a2m5LmgUABYBGAB",
        "score": 0.8192682266,
        "title": "机器<em>学习</em>入门（ 台湾大学李宏毅课程笔记 ）",
        "url": "https://api.zhihu.com/columns/holeung-ml",
        "author": {
          "badge": [],
          "name": "良多趣味",
          "url": "https://api.zhihu.com/people/4d08230f4f24b8176ccb895a7a55a053",
          "type": "people",
          "avatar_url": "https://pic4.zhimg.com/50/v2-8681622780f3cb0a1839e8bf00c732bf_s.jpg",
          "url_token": "liu-hao-liang-36",
          "id": "4d08230f4f24b8176ccb895a7a55a053"
        },
        "avatar_url": "https://pic4.zhimg.com/v2-c80b296c31b9ff094f1dcde1595933db_r.jpg",
        "image_url": "https://pic4.zhimg.com/v2-c80b296c31b9ff094f1dcde1595933db_r.jpg",
        "followers": 1079,
        "type": "column"
      },
      "type": "search_result",
      "id": 117
    },
    {
      "highlight": {
        "content": "专栏主营业务：让更多人能看的懂的机器<em>学习</em>科普+进阶文章。欢迎各位大神投稿或协助审阅",
        "description": "专栏主营业务：让更多人能看的懂的机器<em>学习</em>科普+进阶文章。欢迎各位大神投稿或协助审阅",
        "title": "无痛的机器<em>学习</em>"
      },
      "object": {
        "description": "专栏主营业务：让更多人能看的懂的机器<em>学习</em>科普+进阶文章。欢迎各位大神投稿或协助审阅",
        "is_following": false,
        "id": "hsmyy",
        "articles_count": 76,
        "attached_info_bytes": "OlMKC3BsYWNlaG9sZGVyEiAzOTJmN2NkYzhhOWIyYmM0NjQxNTQyZmJkYWNkZmVhZRgFIgUxNjk1OSoFaHNteXlKDOa3seW6puWtpuS5oFAAWARgAQ==",
        "score": 0.7962349057,
        "title": "无痛的机器<em>学习</em>",
        "url": "https://api.zhihu.com/columns/hsmyy",
        "author": {
          "badge": [],
          "name": "冯超",
          "url": "https://api.zhihu.com/people/3ef5c095dad2c81afb977771cfae27a6",
          "type": "people",
          "avatar_url": "https://pic4.zhimg.com/50/da8e974dc_s.jpg",
          "url_token": "feng-chao",
          "id": "3ef5c095dad2c81afb977771cfae27a6"
        },
        "avatar_url": "https://pic2.zhimg.com/v2-2dab704c99bdbcf46a243362fb47e71f_r.jpg",
        "image_url": "https://pic2.zhimg.com/v2-2dab704c99bdbcf46a243362fb47e71f_r.jpg",
        "followers": 15165,
        "type": "column"
      },
      "type": "search_result",
      "id": 118
    },
    {
      "highlight": {
        "content": "欢迎关注机器<em>学习</em>炼丹记（微信公众号：Julius-AI），一个机器学习从业者的思考和札记",
        "description": "欢迎关注机器<em>学习</em>炼丹记（微信公众号：Julius-AI），一个机器学习从业者的思考和札记",
        "title": "机器<em>学习</em>炼丹记"
      },
      "object": {
        "description": "欢迎关注机器<em>学习</em>炼丹记（微信公众号：Julius-AI），一个机器学习从业者的思考和札记",
        "is_following": false,
        "id": "juliuszh",
        "articles_count": 3,
        "attached_info_bytes": "OlYKC3BsYWNlaG9sZGVyEiAzOTJmN2NkYzhhOWIyYmM0NjQxNTQyZmJkYWNkZmVhZRgFIgU4MTMzMioIanVsaXVzemhKDOa3seW6puWtpuS5oFAAWARgAQ==",
        "score": 0.7914506793,
        "title": "机器<em>学习</em>炼丹记",
        "url": "https://api.zhihu.com/columns/juliuszh",
        "author": {
          "badge": [],
          "name": "Juliuszh",
          "url": "https://api.zhihu.com/people/9f65e9890272246d013f336374f0586a",
          "type": "people",
          "avatar_url": "https://pic3.zhimg.com/50/v2-4a62603159cd7d4c1c4facde0b3813f3_s.jpg",
          "url_token": "junezth",
          "id": "9f65e9890272246d013f336374f0586a"
        },
        "avatar_url": "https://pic2.zhimg.com/v2-220dd4f27bd8564744a2daffb85b8e4c_r.jpg",
        "image_url": "https://pic2.zhimg.com/v2-220dd4f27bd8564744a2daffb85b8e4c_r.jpg",
        "followers": 1456,
        "type": "column"
      },
      "type": "search_result",
      "id": 119
    },
    {
      "highlight": {
        "content": "专注于<em>学习</em>计算机科学相关方向的知识，分享一些自己写的代码，笔记以及一些名校课程的作业",
        "description": "专注于<em>学习</em>计算机科学相关方向的知识，分享一些自己写的代码，笔记以及一些名校课程的作业",
        "title": "马天猫的CS<em>学习</em>之旅"
      },
      "object": {
        "description": "专注于<em>学习</em>计算机科学相关方向的知识，分享一些自己写的代码，笔记以及一些名校课程的作业",
        "is_following": false,
        "id": "deeplearningcat",
        "articles_count": 10,
        "attached_info_bytes": "Ol0KC3BsYWNlaG9sZGVyEiAzOTJmN2NkYzhhOWIyYmM0NjQxNTQyZmJkYWNkZmVhZRgFIgUzOTAxNSoPZGVlcGxlYXJuaW5nY2F0Sgzmt7HluqblrabkuaBQAFgEYAE=",
        "score": 0.7526388764,
        "title": "马天猫的CS<em>学习</em>之旅",
        "url": "https://api.zhihu.com/columns/deeplearningcat",
        "author": {
          "badge": [],
          "name": "马天猫Masn",
          "url": "https://api.zhihu.com/people/58a43f85673f581412d076e212eb1681",
          "type": "people",
          "avatar_url": "https://pic3.zhimg.com/50/v2-bef03feadae3f2c436136c7f4cb76fa8_s.jpg",
          "url_token": "ma-shao-nan-89",
          "id": "58a43f85673f581412d076e212eb1681"
        },
        "avatar_url": "https://pic2.zhimg.com/v2-b59808bd06ed395c6ace0a7bf94ffa61_r.jpg",
        "image_url": "https://pic2.zhimg.com/v2-b59808bd06ed395c6ace0a7bf94ffa61_r.jpg",
        "followers": 465,
        "type": "column"
      },
      "type": "search_result",
      "id": 120
    }
  ],
  "search_action_info": {
    "attached_info_bytes": "OjYSIDM5MmY3Y2RjOGE5YjJiYzQ2NDE1NDJmYmRhY2RmZWFlSgzmt7HluqblrabkuaBQAFgEYAE=",
    "search_hash_id": "392f7cdc8a9b2bc4641542fbdacdfeae"
  }
}